pycatlink/__init__.py
pycatlink/__main__.py
pycatlink/account.py
pycatlink/c08.py
pycatlink/client.py
pycatlink/const.py
pycatlink/device.py
pycatlink/exceptions.py
pycatlink/models.py
pycatlink/py.typed
pycatlink/utils.py
pycatlink-1.0.0a10.dist-info/METADATA
pycatlink-1.0.0a10.dist-info/WHEEL
pycatlink-1.0.0a10.dist-info/licenses/LICENSE.md
pycatlink-1.0.0a10.dist-info/licenses/NOTICE.md
pycatlink-1.0.0a10.dist-info/RECORD
