Metadata-Version: 2.4
Name: pycatlink
Version: 1.0.0a10
Summary: CatLink API Library
License-File: LICENSE.md
License-File: NOTICE.md
Requires-Python: >=3.13
Requires-Dist: aiohttp>=3.8.0
Requires-Dist: cryptography>=41.0.0
Requires-Dist: dataclass-wizard>=0.39.1
Requires-Dist: python-dotenv>=1.2.1
Requires-Dist: typer>=0.21.1
